[{"productImages":{"imageName":"281303","watchVideoLink":"","alternateImageThumbnails":[],"alternateImages":[],"fullImagePostfix":"?$bjs-Initial350$","isThumbnailTiny":false,"thumbNailImage":"https://s7d6.scene7.com/is/image/bjs/281303?$bjs-160$","type":"ProductBean","isThumbnailSmall":false,"url":null,"catalogImageFamilyReceipe":"?$bjs-243$","fullImageZoomer":"https://s7d6.scene7.com/is/image/bjs/281303?$bjs-243$","strImagePath":null,"catalogImagePath":"https://s7d6.scene7.com/is/image/bjs/","catalogImagePathFamily":"https://s7d6.scene7.com/is/image/bjs/","featureThumbnailPostfix":"?$bjs-110$","fullImage":"https://s7d6.scene7.com/is/image/bjs/281303?$bjs-Initial350$","thumbnailPostfix":"?$bjs-160$","productType":null},"defaultB2bMaxQuantity":"999999","descriptiveAttributes":[{"sequenceNumber":0,"usage":"2","name":"Model Number","attributeValueDataBeans":[{"sequenceNumber":0,"name":"20LNS1MV00","value":"20LNS1MV00"}]},{"sequenceNumber":0,"usage":"2","name":"Operating System","attributeValueDataBeans":[{"sequenceNumber":0,"name":"Windows 10","value":"Windows 10"}]},{"sequenceNumber":1,"usage":"2","name":"Estimated Delivery","attributeValueDataBeans":[{"sequenceNumber":1,"name":"3-5 Business Days","value":"3-5 Business Days"}]},{"sequenceNumber":2,"usage":"2","name":"upc","attributeValueDataBeans":[{"sequenceNumber":2,"name":"195477474321","value":"195477474321"}]},{"sequenceNumber":3,"usage":"2","name":"Type","attributeValueDataBeans":[{"sequenceNumber":3,"name":"2-in-1 Touchscreen Laptop","value":"2-in-1 Touchscreen Laptop"}]},{"sequenceNumber":4,"usage":"2","name":"Screen Size Class","attributeValueDataBeans":[{"sequenceNumber":4,"name":"11.6\"","value":"11.6\""}]},{"sequenceNumber":5,"usage":"2","name":"Processor Type","attributeValueDataBeans":[{"sequenceNumber":5,"name":"Intel Celeron","value":"Intel Celeron"}]},{"sequenceNumber":6,"usage":"2","name":"RAM Capacity","attributeValueDataBeans":[{"sequenceNumber":6,"name":"4GB","value":"4GB"}]},{"sequenceNumber":7,"usage":"2","name":"Solid State Drive Capacity","attributeValueDataBeans":[{"sequenceNumber":7,"name":"128GB","value":"128GB"}]},{"sequenceNumber":8,"usage":"2","name":"Touchscreen","attributeValueDataBeans":[{"sequenceNumber":8,"name":"Yes","value":"Yes"}]},{"sequenceNumber":9,"usage":"2","name":"Activity Type","attributeValueDataBeans":[{"sequenceNumber":9,"name":"2-in-1s","value":"2-in-1s"}]},{"sequenceNumber":11,"usage":"2","name":"Color","attributeValueDataBeans":[{"sequenceNumber":11,"name":"Black","value":"Black"}]},{"sequenceNumber":12,"usage":"2","name":"Speakers","attributeValueDataBeans":[{"sequenceNumber":12,"name":"Yes","value":"Yes"}]},{"sequenceNumber":13,"usage":"2","name":"Power Supply","attributeValueDataBeans":[{"sequenceNumber":13,"name":"Standard","value":"Standard"}]},{"sequenceNumber":14,"usage":"2","name":"Battery Type","attributeValueDataBeans":[{"sequenceNumber":14,"name":"Lithium Ion","value":"Lithium Ion"}]},{"sequenceNumber":15,"usage":"2","name":"Average Battery Life","attributeValueDataBeans":[{"sequenceNumber":15,"name":"12 Hours","value":"12 Hours"}]},{"sequenceNumber":16,"usage":"2","name":"Charging Interface","attributeValueDataBeans":[{"sequenceNumber":16,"name":"Standard","value":"Standard"}]},{"sequenceNumber":17,"usage":"2","name":"Bluetooth Enabled","attributeValueDataBeans":[{"sequenceNumber":17,"name":"Yes","value":"Yes"}]},{"sequenceNumber":18,"usage":"2","name":"Wireless Connectivity","attributeValueDataBeans":[{"sequenceNumber":18,"name":"802.11ac Wi-Fi","value":"802.11ac Wi-Fi"}]},{"sequenceNumber":19,"usage":"2","name":"Ethernet Connectivity","attributeValueDataBeans":[{"sequenceNumber":19,"name":"Ethernet LAN","value":"Ethernet LAN"}]},{"sequenceNumber":20,"usage":"2","name":"Graphics","attributeValueDataBeans":[{"sequenceNumber":20,"name":"Intel UHD Graphics 600","value":"Intel UHD Graphics 600"}]},{"sequenceNumber":21,"usage":"2","name":"Display Type","attributeValueDataBeans":[{"sequenceNumber":21,"name":"HD LED-Backlit Touchscreen Display","value":"HD LED-Backlit Touchscreen Display"}]},{"sequenceNumber":22,"usage":"2","name":"Track Pad/Pointing Device","attributeValueDataBeans":[{"sequenceNumber":22,"name":"Touchpad","value":"Touchpad"}]},{"sequenceNumber":23,"usage":"2","name":"Webcam/Microphone","attributeValueDataBeans":[{"sequenceNumber":23,"name":"HD Webcam and Microphone","value":"HD Webcam and Microphone"}]},{"sequenceNumber":24,"usage":"2","name":"ENERGY STAR Certified","attributeValueDataBeans":[{"sequenceNumber":24,"name":"Yes","value":"Yes"}]},{"sequenceNumber":25,"usage":"2","name":"Expansion Slots","attributeValueDataBeans":[{"sequenceNumber":25,"name":"MicroSD Memory Card Reader","value":"MicroSD Memory Card Reader"}]},{"sequenceNumber":26,"usage":"2","name":"Lock Slot/Security Features","attributeValueDataBeans":[{"sequenceNumber":26,"name":"Lock Slot","value":"Lock Slot"}]},{"sequenceNumber":27,"usage":"2","name":"Keyboard","attributeValueDataBeans":[{"sequenceNumber":27,"name":"Yes","value":"Yes"}]},{"sequenceNumber":28,"usage":"2","name":"Software","attributeValueDataBeans":[{"sequenceNumber":28,"name":"Windows 10 Pro 64-bit Edition","value":"Windows 10 Pro 64-bit Edition"}]},{"sequenceNumber":29,"usage":"2","name":"Camera Resolution (Front)","attributeValueDataBeans":[{"sequenceNumber":29,"name":"720p","value":"720p"}]},{"sequenceNumber":30,"usage":"2","name":"Video Recording Resolution","attributeValueDataBeans":[{"sequenceNumber":30,"name":"720p","value":"720p"}]},{"sequenceNumber":31,"usage":"2","name":"Audio Jack","attributeValueDataBeans":[{"sequenceNumber":31,"name":"Yes","value":"Yes"}]},{"sequenceNumber":32,"usage":"2","name":"Warranty","attributeValueDataBeans":[{"sequenceNumber":32,"name":"1 Year","value":"1 Year"}]},{"sequenceNumber":33,"usage":"2","name":"Includes","attributeValueDataBeans":[{"sequenceNumber":33,"name":"Laptop, Power Adapter and User Guide","value":"Laptop, Power Adapter and User Guide"}]},{"sequenceNumber":34,"usage":"2","name":"Item Dimensions","attributeValueDataBeans":[{"sequenceNumber":34,"name":"11.8\"L x 8.3\"W x 0.9\"H","value":"11.8\"L x 8.3\"W x 0.9\"H"}]},{"sequenceNumber":35,"usage":"2","name":"Item Weight","attributeValueDataBeans":[{"sequenceNumber":35,"name":"3.4 lbs.","value":"3.4 lbs."}]}],"bjsrating":{"newestRvwDate":"2022-03-02T05:00:00.000000000Z","avgOvrlRating":5,"largeStarImgLocn":null,"quickReviews":0,"customerVideos":"false","smallStarImgLocn":null,"name":"Lenovo ThinkPad Yoga 20LNS1MV00 Laptop Intel Celeron N4120 Processor 4GB Memory 128GB SSD","fullReviews":15,"customerImages":"false","pageId":"P_281303","oldestRvwDate":"2021-11-13T05:00:00.000000000Z"},"manufacturerPartNumber":"20LNS1MV00","immediateMerchandiseParentId":"3000000000000099215","bjsitems":[{"isSubscriptionEligible":false,"itemStandardPrice":{"symbol":"$","amount":399.99},"offer":{"endDate":"2022-04-01T03:59:59.000000000Z","precedence":50,"startDate":"2022-02-23T05:00:00.000000000Z"},"itemId":"3000000000003391802","isWeightedItem":"false","mapPrice":{"symbol":"$","amount":249.99},"offerDescription":null,"articleId":"281303","instantSavings":true,"partNumber":"281303"}],"merchandiseCatalogId":"10203","storeAttributeDetail":{"Toys":{},"MAX_QUANTITY":"99","TechAdvisorDetail":{"TECHCHAT_URL":"/advisors.content.services_advisors.A.services","TECHADVICE":"1","TECHCHAT_IMAGE":"https://s7d6.scene7.com/is/image/bjs/tech_advisor_chat_button_offline","TECHADVISE_IMAGE":"https://s7d6.scene7.com/is/image/bjs/tech_advisors_icon_2016","TECHADVISE_URL":"/techadvisors"},"WebCollageDetail":{"WEBCOLLAGE_SWITCH":"ON","WEBCOLLAGE_URL":"//gateway.answerscloud.com/bjs/production/gateway.min.js"},"HandyDetails":{}},"immediateParentName":"WOW Deals","partNumber":"P_281303","entitledItems":[{"definingAttributeValueDataBeans":[],"itemID":"3000000000003391802","descriptiveAttributeValueDataBeans":[{"sequenceNumber":0,"name":"1","value":"1","attributeReferenceNumber":"3000000000010145298"},{"sequenceNumber":0,"name":"1","value":"1","attributeReferenceNumber":"3000000000010145299"},{"sequenceNumber":0,"name":"38","value":"38","attributeReferenceNumber":"3000000000010145300"},{"sequenceNumber":0,"name":"114","value":"114","attributeReferenceNumber":"3000000000010145301"},{"sequenceNumber":0,"name":"195477474321","value":"195477474321","attributeReferenceNumber":"3000000000010157125"},{"sequenceNumber":0,"name":"2037953","value":"2037953","attributeReferenceNumber":"3000000000010145616"}],"buyable":1,"manufacturerPartNumber":"20LNS1MV00","descriptiveAttributeDataBeans":[{"sequenceNumber":-1,"usage":"2","name":"CVQuantity","attributeReferenceNumber":"3000000000010145299"},{"sequenceNumber":-1,"usage":"2","name":"EAQuantity","attributeReferenceNumber":"3000000000010145298"},{"sequenceNumber":-1,"usage":"2","name":"LAYQuantity","attributeReferenceNumber":"3000000000010145300"},{"sequenceNumber":-1,"usage":"2","name":"PALQuantity","attributeReferenceNumber":"3000000000010145301"},{"sequenceNumber":-1,"usage":"2","name":"gtin","attributeReferenceNumber":"3000000000010157125"},{"sequenceNumber":1,"usage":"2","name":"GSC","attributeReferenceNumber":"3000000000010145616"}],"articleId":"281303","partNumber":"281303","calculatedContractPrice":{"symbol":"$","amount":249.99},"onSpecial":0,"description":{"itemId":"3000000000003391802","available":1,"fullImage":"https://s7d6.scene7.com/is/image/bjs/281303?$bjs-400$","language_id":-1,"shortDescription":"LENOVO THINKPAD YOGA 2-IN-1 LAPTOP","name":"Lenovo ThinkPad Yoga 20LNS1MV00 Laptop, Intel Celeron N4120 Processor, 4GB Memory, 128GB SSD","published":1,"longDescription":"The Lenovo ThinkPad Yoga 11e laptop features a 360° hinge to interact with apps or browse with the 10-point multi-touch HD display. Position it as a tent to watch videos or use it as a laptop for working with the full-sized keyboard. The ThinkPad Yoga 11e helps you write, sketch, annotate documents, take notes, and more. With up to 12 hours of battery life, the ThinkPad Yoga 11e will last for a full day of work.<BR><BR>The laptop includes a wide range of ports including USB Type-C, standard USB Type-A, HDMI video connector, RJ45 Ethernet for fast internet connectivity, 3.5mm combo audio/mic jack, and a MicroSD memory card reader. The 4GB DDR4 SDRAM of memory is a fast 2400MHz and the 128GB SSD drive is a PCIe M.2 NVMe storage device.<BR><BR>With its optional ThinkPad Pen Pro, the ThinkPad Yoga 11e helps unleash the imagination. You can write, sketch, annotate documents, take notes, and more.<BR><BR><SPAN style='font-weight:bold;'>Product Features:</SPAN><BR><BR><DIV><LI>Operating System: Windows 10 Pro 64-bit<LI>Processor: Intel Celeron N4120 1.1GHz quad-core (Max Speed 2.6GHz)<LI>Display: 11.6\" HD LED-backlit touchscreen<LI>Hard Drive: 128GB SSD storage<LI>Memory: 4GB DDR4 SDRAM<LI>Graphics: Intel UHD 600<LI>HD webcam with Dolby audio stereo speakers and microphone<LI>802.11ac Wi-Fi and Bluetooth wireless<LI>Ports: 2x USB 3.1 Gen1, USB Type-C 3.1 Gen1, HDMI, Ethernet LAN, Headphone/Microphone Jack and MicroSD memory card reader<LI>Convertible laptop with 360° hinge for the tablet to laptop modes<LI>Includes laptop, power adapter, and user guide<LI>Warranty: 1 year</DIV><BR>(Model 20LNS1MV00)"}}],"productUOM":{"3000000000003391802":"C62"},"gtin":[],"featureNames":[],"itemPrices":{"3000000000003391802":{"itemDisc":150,"priceStrike":399.99,"offerPrice":249.99,"mapPrice":249.99}},"hiddenAttr":[{"usage":"2","sequenceNumber":-1,"name":"CVQuantity","attributeValueDataBeans":[{"sequenceNumber":0,"name":"1","value":"1"}]},{"usage":"2","sequenceNumber":-1,"name":"Cm21lastchance","attributeValueDataBeans":[{"sequenceNumber":-1,"name":"Last Chance Black Friday Deals","value":"Last Chance Black Friday Deals"}]},{"usage":"2","sequenceNumber":-1,"name":"Cm21new","attributeValueDataBeans":[{"sequenceNumber":-1,"name":"New Cyber Week Deals","value":"New Cyber Week Deals"}]},{"usage":"2","sequenceNumber":-1,"name":"EAQuantity","attributeValueDataBeans":[{"sequenceNumber":0,"name":"1","value":"1"}]},{"usage":"2","sequenceNumber":-1,"name":"Free_Shipping","attributeValueDataBeans":[{"sequenceNumber":-1,"name":"Y","value":"Y"}]},{"usage":"2","sequenceNumber":-1,"name":"Gifting21tech","attributeValueDataBeans":[{"sequenceNumber":-1,"name":"Tech Deals","value":"Tech Deals"}]},{"usage":"2","sequenceNumber":-1,"name":"ItemMaxQuantity","attributeValueDataBeans":[{"sequenceNumber":-1,"name":"3","value":"3"}]},{"usage":"2","sequenceNumber":-1,"name":"Keywords","attributeValueDataBeans":[{"sequenceNumber":-1,"name":"281303, Lenovo, 20LNS1MV00, Laptops, ThinkPad, Yoga, Intel, Celeron, N4120, Processor, 4GB, Memory, 128GB, SSD, Windows 10","value":"281303, Lenovo, 20LNS1MV00, Laptops, ThinkPad, Yoga, Intel, Celeron, N4120, Processor, 4GB, Memory, 128GB, SSD, Windows 10"}]},{"usage":"2","sequenceNumber":-1,"name":"LAYQuantity","attributeValueDataBeans":[{"sequenceNumber":0,"name":"38","value":"38"}]},{"usage":"2","sequenceNumber":-1,"name":"PALQuantity","attributeValueDataBeans":[{"sequenceNumber":0,"name":"114","value":"114"}]},{"usage":"2","sequenceNumber":-1,"name":"SFC","attributeValueDataBeans":[{"sequenceNumber":0,"name":"N","value":"N"}]},{"usage":"2","sequenceNumber":-1,"name":"ShowPriceCartPostLogin","attributeValueDataBeans":[{"sequenceNumber":-1,"name":"N","value":"N"}]},{"usage":"2","sequenceNumber":-1,"name":"Windows","attributeValueDataBeans":[{"sequenceNumber":-1,"name":"Windows Operating System","value":"Windows Operating System"}]}],"maximumItemPrice":{"symbol":"$","amount":249.99,"catEntryId":null},"minimumItemPrice":{"symbol":"$","amount":249.99,"catEntryId":null},"maxItemPrice":"$249.99","immediateParentId":"3000000000000175488","manufacturerName":"Lenovo","definingAttributes":[],"minItemPrice":"$249.99","itemAvailDetails":{"3000000000003391802":{"itemAvailableInClub":"Y","itemAvailableOnline":"Y"}},"bjsItemsInventory":[{"itemId":"3000000000003391802","availInventory":true}],"userData":{"B2CPdpQAKillSwitch":"OFF","killSwitchCoupon":"OFF","killSwitchGC":"OFF","killSwitchMicroService":"ON","killSwitchItemEligibilityEngine":"OFF","killSwitchEGC":"OFF","killSwitchShippingRestriction":"OFF","B2CPdpBundlesKillSwitch":"OFF","killSwitchBOPIC":"ON","killSwitchPdpMagicZoomViewer":"OFF","B2CPdpWhyDidYouBuyKillSwitch":"ON"},"warrantyInformation":{"3000000000003391802":{"WarrantyCatEntryId":"3000000000001568752","itemDisc":0,"priceStrike":49.99,"offerPrice":49.99,"warrantyImageInfo":"https://bjs.scene7.com/is/image/bjs/protection_Plus_new?$bjs-65$","OnlineInventoryAvialable":true,"name":"BJ's Protection Plus 3-Year Service Plan for Laptops, Tablets, Notebooks, Cameras","warrantyYears":"3"}},"productType":"ProductBean","merchandiseCatagoryIdentifier":"402020179","isPromoItemLevelAvail":false,"description":{"name":"Lenovo ThinkPad Yoga 20LNS1MV00 Laptop, Intel Celeron N4120 Processor, 4GB Memory, 128GB SSD"},"productSeoData":[{"meta_desc":"Shop the Lenovo ThinkPad Yoga 20LNS1MV00 Laptop with Intel Celeron N4120 Processor, 4GB Memory and 128GB SSD from BJs.com. Order online today!","meta_keyword":null,"title":"Lenovo ThinkPad Yoga 20LNS1MV00 Laptop"}],"breadCrumbDetail":[{"1":"Computers & Tablets|/category/computers-and-tablets/3000000000000144986","2":"Computers|/category/computers-and-tablets/computers/743","3":"Laptops|/category/computers-and-tablets/computers/laptops/747","4":[],"5":[]},{"1":"Seasonal Home|/category/seasonal-home/3000000000000186497","2":"Last Minute Gift & Prep|/category/seasonal-home/last-minute-gift-and-prep/3000000000000234491","3":[],"4":[],"5":[]},{"1":"WOW Deals|/category/wow-deals/3000000000000175488","2":[],"3":[],"4":[],"5":[]}],"itemAvailDetailsELIG":{"Eligibility":[{"articleId":"281303","itemType":"CLUB_ONLINE","program":{"sdd":{"N":["0001","0007","0008","0010","0011","0013","0015","0017","0018","0019","0020","0021","0022","0023","0025","0026","0027","0029","0030","0031","0032","0033","0034","0035","0036","0037","0038","0039","0040","0041","0044","0045","0046","0047","0048","0049","0050","0051","0052","0053","0054","0055","0056","0057","0058","0059","0060","0061","0062","0063","0064","0066","0067","0068","0069","0070","0071","0072","0073","0074","0075","0076","0077","0078","0079","0084","0085","0086","0091","0092","0093","0094","0096","0097","0100","0101","0102","0105","0106","0107","0108","0109","0110","0111","0112","0113","0114","0115","0116","0117","0118","0119","0120","0122","0123","0124","0125","0126","0127","0128","0129","0130","0131","0132","0133","0134","0135","0136","0138","0139","0141","0142","0143","0144","0146","0147","0148","0150","0151","0152","0153","0154","0156","0159","0160","0162","0165","0167","0168","0169","0170","0171","0172","0173","0174","0175","0176","0177","0178","0179","0180","0181","0183","0184","0185","0186","0188","0189","0190","0191","0192","0193","0195","0197","0198","0199","0200","0201","0203","0204","0205","0206","0207","0208","0209","0210","0211","0212","0213","0214","0215","0216","0219","0220","0221","0301","0302","0303","0306","0307","0308","0309","0310","0311","0312","0314","0315","0316","0317","0318","0319","0320","0321","0322","0350","0351","0352","0353","0354","0355","0357","0359","0360","0361","0363","0365","0366","0367","0368","0369","0370","0371","0374","0377","0378","0382","0383","0384","0385","0372","0364","0381","0388","0386","0223","0387","0389"]},"bopic":{"Y":["0001","0007","0008","0010","0011","0013","0015","0017","0018","0019","0020","0021","0022","0023","0025","0026","0027","0029","0030","0031","0033","0034","0035","0037","0038","0039","0040","0041","0044","0045","0046","0047","0048","0049","0050","0052","0053","0055","0056","0057","0058","0059","0060","0061","0062","0063","0064","0066","0067","0068","0069","0071","0072","0073","0074","0075","0076","0077","0078","0079","0084","0085","0086","0092","0093","0094","0096","0097","0100","0101","0102","0105","0112","0113","0115","0116","0117","0119","0122","0124","0127","0131","0132","0136","0138","0139","0141","0142","0143","0148","0153","0156","0159","0160","0162","0165","0167","0168","0172","0173","0175","0176","0178","0184","0185","0189","0190","0192","0193","0195","0197","0198","0200","0201","0203","0204","0205","0206","0207","0208","0209","0210","0211","0212","0213","0214","0216","0220","0301","0302","0303","0306","0307","0308","0309","0310","0311","0312","0314","0315","0316","0317","0318","0319","0320","0321","0322","0350","0351","0352","0353","0354","0355","0359","0360","0363","0366","0368","0369","0370","0371","0374","0377","0383","0384","0385","0372","0364","0381","0388","0386","0223","0387","0389"],"N":["0174","0130","0054","0051","0170","0171","0091","0128","0367","0169","0125","0126","0365","0123","0129","0186","0183","0382","0181","0180","0215","0378","0134","0179","0135","0177","0133","0219","0152","0032","0150","0151","0191","0070","0106","0147","0146","0221","0188","0144","0109","0107","0108","0361","0120","0114","0357","0036","0154","0110","0199","0111","0118"]}},"articleEBT":"N","attributes":{"clubEBT":{"Y":[],"N":["0116","0318","0388","0352","0048","0372","0193","0354","0107","0195","0020","0377","0190","0077","0311","0068","0052","0169","0359","0018","0366","0044","0173","0206","0114","0128","0197","0192","0142","0180","0148","0307","0386","0176","0118","0208","0106","0184","0381","0046","0315","0365","0022","0174","0124","0369","0220","0209","0034","0382","0200","0053","0172","0319","0152","0378","0021","0071","0207","0078","0308","0069","0086","0223","0147","0351","0062","0216","0026","0384","0045","0112","0170","0129","0364","0027","0387","0117","0181","0057","0007","0204","0067","0017","0199","0110","0127","0177","0165","0219","0013","0049","0191","0096","0306","0133","0100","0055","0091","0186","0029","0079","0092","0201","0061","0368","0054","0175","0143","0125","0363","0070","0050","0138","0188","0094","0309","0033","0316","0385","0215","0105","0119","0123","0320","0178","0361","0317","0097","0355","0130","0108","0205","0132","0151","0058","0035","0357","0085","0030","0008","0213","0001","0111","0074","0367","0221","0353","0168","0303","0156","0126","0134","0056","0350","0037","0189","0040","0064","0072","0154","0321","0039","0073","0023","0371","0135","0185","0211","0102","0310","0019","0051","0036","0162","0214","0047","0120","0314","0179","0198","0167","0109","0159","0038","0160","0075","0115","0025","0210","0374","0063","0141","0183","0150","0031","0015","0041","0389","0136","0059","0301","0302","0383","0011","0212","0084","0322","0139","0066","0093","0171","0010","0060","0144","0122","0312","0153","0146","0032","0203","0360","0101","0131","0113","0370","0076"]}}}]},"isMajorAppliance":false,"isBNPLCategory":true}]